{
    "network": "Planeta", 
    "operator": "Planeta", 
    "routes": {
        "10": [
            {
                "exceptions": [], 
                "from": "Guarapari", 
                "service": [
                    "Mo-Sa"
                ], 
                "stations": [
                    "Guarapari", 
                    "Jaqueira"
                ], 
                "times": [
                    [
                        "05:30", 
                        "06:30"
                    ], 
                    [
                        "06:40", 
                        "07:40"
                    ], 
                    [
                        "07:40", 
                        "08:40"
                    ], 
                    [
                        "09:30", 
                        "10:30"
                    ], 
                    [
                        "12:30", 
                        "13:30"
                    ], 
                    [
                        "16:30", 
                        "17:30"
                    ], 
                    [
                        "19:15", 
                        "20:15"
                    ]
                ], 
                "to": "Jaqueira"
            }
        ], 
        "11": [
            {
                "exceptions": [], 
                "from": "Jaqueira", 
                "service": [
                    "Mo-Sa"
                ], 
                "stations": [
                    "Jaqueira", 
                    "Guarapari"
                ], 
                "times": [
                    [
                        "06:10", 
                        "07:10"
                    ], 
                    [
                        "07:10", 
                        "08:10"
                    ], 
                    [
                        "08:15", 
                        "09:15"
                    ], 
                    [
                        "10:20", 
                        "11:20"
                    ], 
                    [
                        "13:00", 
                        "14:00"
                    ], 
                    [
                        "17:30", 
                        "18:30"
                    ], 
                    [
                        "19:40", 
                        "20:40"
                    ]
                ], 
                "to": "Guarapari"
            }
        ], 
        "26": [
            {
                "exceptions": [], 
                "from": "Cachoeiro de Itapemirim", 
                "service": [
                    "Mo-Sa"
                ], 
                "stations": [
                    "Cachoeiro de Itapemirim", 
                    "Guarapari"
                ], 
                "times": [
                    [
                        "09:40", 
                        "10:40"
                    ]
                ], 
                "to": "Guarapari"
            }
        ], 
        "27": [
            {
                "exceptions": [], 
                "from": "Guarapari", 
                "service": [
                    "Mo-Su"
                ], 
                "stations": [
                    "Guarapari", 
                    "Cachoeiro de Itapemirim"
                ], 
                "times": [
                    [
                        "14:30", 
                        "15:30"
                    ]
                ], 
                "to": "Cachoeiro de Itapemirim"
            }
        ], 
        "28": [
            {
                "exceptions": [], 
                "from": "Vila Velha", 
                "service": [
                    "Mo-Su"
                ], 
                "stations": [
                    "Vila Velha", 
                    "Bom Jesus do Norte"
                ], 
                "times": [
                    [
                        "06:00", 
                        "07:00"
                    ], 
                    [
                        "16:00", 
                        "17:00"
                    ]
                ], 
                "to": "Bom Jesus do Norte"
            }
        ], 
        "29": [
            {
                "exceptions": [], 
                "from": "Bom Jesus do Norte", 
                "service": [
                    "Mo-Su"
                ], 
                "stations": [
                    "Bom Jesus do Norte", 
                    "Vila Velha"
                ], 
                "times": [
                    [
                        "06:30", 
                        "07:30"
                    ], 
                    [
                        "15:50", 
                        "16:50"
                    ]
                ], 
                "to": "Vila Velha"
            }
        ], 
        "33": [
            {
                "exceptions": [], 
                "from": "Dom Bosco", 
                "service": [
                    "Mo-Sa"
                ], 
                "stations": [
                    "Dom Bosco", 
                    "Bahia Nova"
                ], 
                "times": [
                    [
                        "12:00", 
                        "13:00"
                    ], 
                    [
                        "18:00", 
                        "19:00"
                    ]
                ], 
                "to": "Bahia Nova"
            }
        ], 
        "34": [
            {
                "exceptions": [], 
                "from": "Bahia Nova", 
                "service": [
                    "Mo-Sa"
                ], 
                "stations": [
                    "Bahia Nova", 
                    "Dom Bosco"
                ], 
                "times": [
                    [
                        "06:00", 
                        "07:00"
                    ], 
                    [
                        "15:00", 
                        "16:00"
                    ]
                ], 
                "to": "Dom Bosco"
            }
        ], 
        "43": [
            {
                "exceptions": [], 
                "from": "Guarapari", 
                "service": [
                    "Mo-Sa"
                ], 
                "stations": [
                    "Guarapari", 
                    "Anchieta"
                ], 
                "times": [
                    [
                        "05:30", 
                        "06:30"
                    ], 
                    [
                        "10:00", 
                        "11:00"
                    ], 
                    [
                        "17:00", 
                        "18:00"
                    ]
                ], 
                "to": "Anchieta"
            }
        ], 
        "44": [
            {
                "exceptions": [], 
                "from": "Anchieta", 
                "service": [
                    "Mo-Sa"
                ], 
                "stations": [
                    "Anchieta", 
                    "Guarapari"
                ], 
                "times": [
                    [
                        "06:40", 
                        "07:40"
                    ], 
                    [
                        "11:30", 
                        "12:30"
                    ], 
                    [
                        "18:30", 
                        "19:30"
                    ]
                ], 
                "to": "Guarapari"
            }
        ], 
        "47": [
            {
                "exceptions": [], 
                "from": "Castelo", 
                "service": [
                    "Mo,Fr"
                ], 
                "stations": [
                    "Castelo", 
                    "Venda Nova do Imigrante"
                ], 
                "times": [
                    [
                        "05:30", 
                        "06:30"
                    ]
                ], 
                "to": "Venda Nova do Imigrante"
            }
        ], 
        "48": [
            {
                "exceptions": [], 
                "from": "Venda Nova do Imigrante", 
                "service": [
                    "Mo,Fr"
                ], 
                "stations": [
                    "Venda Nova do Imigrante", 
                    "Castelo"
                ], 
                "times": [
                    [
                        "07:10", 
                        "08:10"
                    ]
                ], 
                "to": "Castelo"
            }
        ], 
        "49": [
            {
                "exceptions": [], 
                "from": "Dom Bosco", 
                "service": [
                    "Mo-Su"
                ], 
                "stations": [
                    "Dom Bosco", 
                    "Ipiranga"
                ], 
                "times": [
                    [
                        "05:10", 
                        "06:20"
                    ], 
                    [
                        "05:30", 
                        "06:40"
                    ], 
                    [
                        "06:00", 
                        "07:10"
                    ], 
                    [
                        "06:30", 
                        "07:40"
                    ], 
                    [
                        "07:00", 
                        "08:10"
                    ], 
                    [
                        "07:30", 
                        "08:40"
                    ], 
                    [
                        "08:00", 
                        "09:10"
                    ], 
                    [
                        "08:30", 
                        "09:40"
                    ], 
                    [
                        "09:00", 
                        "10:10"
                    ], 
                    [
                        "09:30", 
                        "10:40"
                    ], 
                    [
                        "10:00", 
                        "11:10"
                    ], 
                    [
                        "10:30", 
                        "11:40"
                    ], 
                    [
                        "11:00", 
                        "12:10"
                    ], 
                    [
                        "11:30", 
                        "12:40"
                    ], 
                    [
                        "12:00", 
                        "13:10"
                    ], 
                    [
                        "12:30", 
                        "13:40"
                    ], 
                    [
                        "13:00", 
                        "14:10"
                    ], 
                    [
                        "13:30", 
                        "14:40"
                    ], 
                    [
                        "14:00", 
                        "15:10"
                    ], 
                    [
                        "14:30", 
                        "15:40"
                    ], 
                    [
                        "15:00", 
                        "16:10"
                    ], 
                    [
                        "15:30", 
                        "16:40"
                    ], 
                    [
                        "16:00", 
                        "17:10"
                    ], 
                    [
                        "16:30", 
                        "17:40"
                    ], 
                    [
                        "17:00", 
                        "18:10"
                    ], 
                    [
                        "17:30", 
                        "18:40"
                    ], 
                    [
                        "18:00", 
                        "19:10"
                    ], 
                    [
                        "18:30", 
                        "19:40"
                    ], 
                    [
                        "19:00", 
                        "20:10"
                    ], 
                    [
                        "19:30", 
                        "20:40"
                    ], 
                    [
                        "20:00", 
                        "21:10"
                    ], 
                    [
                        "20:30", 
                        "21:40"
                    ]
                ], 
                "to": "Ipiranga"
            }
        ], 
        "5": [
            {
                "exceptions": [], 
                "from": "Cachoeiro de Itapemirim", 
                "service": [
                    "Mo-Su"
                ], 
                "stations": [
                    "Cachoeiro de Itapemirim", 
                    "Guarapari"
                ], 
                "times": [
                    [
                        "05:45", 
                        "06:45"
                    ], 
                    [
                        "08:10", 
                        "09:10"
                    ], 
                    [
                        "10:35", 
                        "11:35"
                    ], 
                    [
                        "13:30", 
                        "14:30"
                    ], 
                    [
                        "14:50", 
                        "15:50"
                    ], 
                    [
                        "17:30", 
                        "18:30"
                    ]
                ], 
                "to": "Guarapari"
            }
        ], 
        "50": [
            {
                "exceptions": [], 
                "from": "Ipiranga", 
                "service": [
                    "Mo-Su"
                ], 
                "stations": [
                    "Ipiranga", 
                    "Dom Bosco"
                ], 
                "times": [
                    [
                        "05:10", 
                        "06:24"
                    ], 
                    [
                        "05:30", 
                        "06:44"
                    ], 
                    [
                        "06:00", 
                        "07:14"
                    ], 
                    [
                        "06:30", 
                        "07:44"
                    ], 
                    [
                        "07:00", 
                        "08:14"
                    ], 
                    [
                        "07:30", 
                        "08:44"
                    ], 
                    [
                        "08:00", 
                        "09:14"
                    ], 
                    [
                        "08:30", 
                        "09:44"
                    ], 
                    [
                        "09:00", 
                        "10:14"
                    ], 
                    [
                        "09:30", 
                        "10:44"
                    ], 
                    [
                        "10:00", 
                        "11:14"
                    ], 
                    [
                        "10:30", 
                        "11:44"
                    ], 
                    [
                        "11:00", 
                        "12:14"
                    ], 
                    [
                        "11:30", 
                        "12:44"
                    ], 
                    [
                        "12:00", 
                        "13:14"
                    ], 
                    [
                        "12:30", 
                        "13:44"
                    ], 
                    [
                        "13:00", 
                        "14:14"
                    ], 
                    [
                        "13:30", 
                        "14:44"
                    ], 
                    [
                        "14:00", 
                        "15:14"
                    ], 
                    [
                        "14:30", 
                        "15:44"
                    ], 
                    [
                        "15:00", 
                        "16:14"
                    ], 
                    [
                        "15:30", 
                        "16:44"
                    ], 
                    [
                        "16:00", 
                        "17:14"
                    ], 
                    [
                        "16:30", 
                        "17:44"
                    ], 
                    [
                        "17:00", 
                        "18:14"
                    ], 
                    [
                        "17:30", 
                        "18:44"
                    ], 
                    [
                        "18:00", 
                        "19:14"
                    ], 
                    [
                        "18:30", 
                        "19:44"
                    ], 
                    [
                        "19:00", 
                        "20:14"
                    ], 
                    [
                        "19:30", 
                        "20:44"
                    ], 
                    [
                        "20:00", 
                        "21:14"
                    ], 
                    [
                        "20:30", 
                        "21:44"
                    ]
                ], 
                "to": "Dom Bosco"
            }
        ], 
        "51": [], 
        "52": [], 
        "6": [
            {
                "exceptions": [], 
                "from": "Guarapari", 
                "service": [
                    "Mo-Sa"
                ], 
                "stations": [
                    "Guarapari", 
                    "Cachoeiro de Itapemirim"
                ], 
                "times": [
                    [
                        "05:20", 
                        "06:20"
                    ], 
                    [
                        "06:00", 
                        "07:00"
                    ], 
                    [
                        "09:40", 
                        "10:40"
                    ], 
                    [
                        "11:00", 
                        "12:00"
                    ], 
                    [
                        "15:40", 
                        "16:40"
                    ], 
                    [
                        "17:15", 
                        "18:15"
                    ]
                ], 
                "to": "Cachoeiro de Itapemirim"
            }
        ]
    }, 
    "source": "http://www.viacaoplaneta-es.com.br/destinos-e-horarios-viacao-planeta/", 
    "updated": "2017-04-28"
}